{
  "data": [
    [
      [
        1,
        null,
        0,
        0.0
      ],
      [
        1.281304651854849,
        6.190386772155762,
        {
          "__enum__": "StatusType.SUCCESS"
        },
        1626150829.3012228,
        1626150835.562711,
        {}
      ]
    ],
    [
      [
        2,
        null,
        0,
        0.0
      ],
      [
        1.2832294197444054,
        6.028400182723999,
        {
          "__enum__": "StatusType.SUCCESS"
        },
        1626150836.47771,
        1626150842.554038,
        {}
      ]
    ],
    [
      [
        3,
        null,
        0,
        0.0
      ],
      [
        1.2804446876198574,
        7.469833850860596,
        {
          "__enum__": "StatusType.SUCCESS"
        },
        1626150843.254099,
        1626150850.776994,
        {}
      ]
    ],
    [
      [
        4,
        null,
        0,
        0.0
      ],
      [
        1.293216901659137,
        5.932477951049805,
        {
          "__enum__": "StatusType.SUCCESS"
        },
        1626150851.6400352,
        1626150857.632829,
        {}
      ]
    ]
  ],
  "config_origins": {
    "1": "Sobol",
    "2": "Random Search (sorted)",
    "3": "Random Search (sorted)",
    "4": "Random Search (sorted)"
  },
  "configs": {
    "1": {
      "feature_selector__percentile": 50,
      "model__max_depth": 17,
      "model__max_features": "log2",
      "model__min_samples_leaf": 0.005050000000000001,
      "preprocessor__categorical_transformer__category_combiner__combine_categories": "no",
      "preprocessor__numeric_transformer__log_creator__take_log": "no"
    },
    "2": {
      "feature_selector__percentile": 87,
      "model__max_depth": 31,
      "model__max_features": "log2",
      "model__min_samples_leaf": 0.004962897731139364,
      "preprocessor__categorical_transformer__category_combiner__combine_categories": "yes",
      "preprocessor__numeric_transformer__log_creator__take_log": "yes"
    },
    "3": {
      "feature_selector__percentile": 46,
      "model__max_depth": 24,
      "model__max_features": "sqrt",
      "model__min_samples_leaf": 0.00636265407545667,
      "preprocessor__categorical_transformer__category_combiner__combine_categories": "yes",
      "preprocessor__numeric_transformer__log_creator__take_log": "no"
    },
    "4": {
      "feature_selector__percentile": 10,
      "model__max_depth": 20,
      "model__max_features": "sqrt",
      "model__min_samples_leaf": 0.007557608640304671,
      "preprocessor__categorical_transformer__category_combiner__combine_categories": "no",
      "preprocessor__numeric_transformer__log_creator__take_log": "yes"
    }
  }
}